ctapipe_io_zfits/__init__.py
ctapipe_io_zfits/_version.py
ctapipe_io_zfits/conftest.py
ctapipe_io_zfits/dl0.py
ctapipe_io_zfits/instrument.py
ctapipe_io_zfits/multifile.py
ctapipe_io_zfits/paths.py
ctapipe_io_zfits/time.py
ctapipe_io_zfits/version.py
ctapipe_io_zfits/resources/LSTCam.camgeom.fits.gz
ctapipe_io_zfits/resources/LSTCam.camreadout.fits.gz
ctapipe_io_zfits/resources/array-element-ids.json
ctapipe_io_zfits/resources/array_element_positions_ctao_n.ecsv
ctapipe_io_zfits/resources/subarray-ids.json
ctapipe_io_zfits/tests/__init__.py
ctapipe_io_zfits/tests/test_dl0.py
ctapipe_io_zfits/tests/test_instrument.py
ctapipe_io_zfits/tests/test_multifiles.py
ctapipe_io_zfits/tests/test_paths.py
ctapipe_io_zfits/tests/test_time.py
ctapipe_io_zfits-0.4.3.dist-info/licenses/LICENSE
ctapipe_io_zfits-0.4.3.dist-info/METADATA
ctapipe_io_zfits-0.4.3.dist-info/WHEEL
ctapipe_io_zfits-0.4.3.dist-info/entry_points.txt
ctapipe_io_zfits-0.4.3.dist-info/top_level.txt
ctapipe_io_zfits-0.4.3.dist-info/RECORD
